musicalbeeps/__init__.py
musicalbeeps/beepsplayer.py
musicalbeeps/script.py
musicalbeeps-0.2.9.dist-info/LICENSE
musicalbeeps-0.2.9.dist-info/METADATA
musicalbeeps-0.2.9.dist-info/WHEEL
musicalbeeps-0.2.9.dist-info/entry_points.txt
musicalbeeps-0.2.9.dist-info/top_level.txt
musicalbeeps-0.2.9.dist-info/RECORD
