Metadata-Version: 2.1
Name: musicalbeeps
Version: 0.2.9
Summary: Play sound beeps corresponding to musical notes.
Home-page: https://github.com/MaelDrapier/musicalbeeps
Author: Maël Drapier
Author-email: mael.drapier@gmail.com
License: MIT
Keywords: music musical note notes beep beeps play player sound frequency
Platform: UNKNOWN
Classifier: Programming Language :: Python :: 3
Classifier: License :: OSI Approved :: MIT License
Classifier: Environment :: Console
Classifier: Intended Audience :: End Users/Desktop
Classifier: Topic :: Multimedia :: Sound/Audio
Classifier: Topic :: Multimedia :: Sound/Audio :: Players
